encourage/__init__.py
encourage/handler/__init__.py
encourage/handler/conversation_handler.py
encourage/llm/__init__.py
encourage/llm/batch_handler.py
encourage/llm/inference_runner.py
encourage/llm/response.py
encourage/llm/response_wrapper.py
encourage/llm/vllm_classes.py
encourage/metrics/__init__.py
encourage/metrics/answer_faithfulness.py
encourage/metrics/answer_relevance.py
encourage/metrics/answer_similarity.py
encourage/metrics/classic.py
encourage/metrics/context_precision.py
encourage/metrics/context_recall.py
encourage/metrics/metric.py
encourage/metrics/non_answer_critic.py
encourage/metrics/number_match.py
encourage/metrics/registry.py
encourage/prompts/__init__.py
encourage/prompts/context.py
encourage/prompts/conversation.py
encourage/prompts/meta_data.py
encourage/prompts/prompt.py
encourage/prompts/prompt_collection.py
encourage/prompts/prompt_reformatter.py
encourage/prompts/templates/default.j2
encourage/prompts/templates/llama3_conv.j2
encourage/prompts/templates/test_template.j2
encourage/prompts/templates/metrics/answer_extraction.j2
encourage/prompts/templates/metrics/answer_faithfulness_nli.j2
encourage/prompts/templates/metrics/answer_faithfulness_split.j2
encourage/prompts/templates/metrics/answer_relevance.j2
encourage/prompts/templates/metrics/context_precision.j2
encourage/prompts/templates/metrics/context_recall.j2
encourage/prompts/templates/metrics/non_answer_critic.j2
encourage/rag/__init__.py
encourage/rag/base_impl.py
encourage/rag/bm25.py
encourage/rag/hybrid_bm25.py
encourage/rag/hyde.py
encourage/rag/hyde_reranker.py
encourage/rag/known_context.py
encourage/rag/no_context.py
encourage/rag/reranker.py
encourage/rag/self_rag.py
encourage/rag/summarize.py
encourage/rag/base/config.py
encourage/rag/base/enum.py
encourage/rag/base/factory.py
encourage/rag/base/interface.py
encourage/rag/rerank/base.py
encourage/rag/rerank/factory.py
encourage/rag/rerank/models.py
encourage/utils/__init__.py
encourage/utils/file_manager.py
encourage_rag-0.3.7.6.dist-info/licenses/LICENSE.txt
encourage_rag-0.3.7.6.dist-info/METADATA
encourage_rag-0.3.7.6.dist-info/WHEEL
encourage_rag-0.3.7.6.dist-info/top_level.txt
encourage_rag-0.3.7.6.dist-info/RECORD
