Metadata-Version: 2.4
Name: encourage-rag
Version: 0.3.7.6
Summary: ENCOURAGE
Author-email: Jan Strich & dida Datenschmiede GmbH <jan.strich@uni-hamburg.de>
Requires-Python: >=3.12
License-File: LICENSE.txt
Requires-Dist: bert-score>=0.3.13
Requires-Dist: chromadb>=1.4.1
Requires-Dist: evaluate>=0.4.3
Requires-Dist: ir-measures>=0.3.7
Requires-Dist: jinja2>=3.1.6
Requires-Dist: mlflow>=3.5.0
Requires-Dist: msgspec==0.20.0
Requires-Dist: nltk>=3.9.1
Requires-Dist: opentelemetry-exporter-otlp-proto-grpc==1.39.1
Requires-Dist: openai>=1.98.0
Requires-Dist: pre-commit>=4.2.0
Requires-Dist: pydantic>=2.12.5
Requires-Dist: PyYAML>=6.0.2
Requires-Dist: qdrant-client>=1.14.2
Requires-Dist: rank-bm25>=0.2.2
Requires-Dist: rouge-score>=0.1.2
Requires-Dist: sentence-transformers>=4.1.0
Requires-Dist: tomlkit>=0.13.2
Requires-Dist: tornado>=6.5
Requires-Dist: tqdm==4.67.1
Requires-Dist: types-PyYAML>=6.0.12.20250516
Requires-Dist: uv>=0.9.6
Provides-Extra: dev
Requires-Dist: jupyterlab>=4.0; extra == "dev"
Requires-Dist: jupytext>=1.16.3; extra == "dev"
Requires-Dist: notebook>=7.4.2; extra == "dev"
Requires-Dist: matplotlib>=3.9.1; extra == "dev"
Requires-Dist: ipywidgets>=8.1.5; extra == "dev"
Requires-Dist: tuna==0.5.11; extra == "dev"
Provides-Extra: ci
Requires-Dist: ruff; extra == "ci"
Requires-Dist: isort; extra == "ci"
Requires-Dist: pytest; extra == "ci"
Requires-Dist: jsondiff; extra == "ci"
Requires-Dist: pytest-cov>=5.0.0; extra == "ci"
Requires-Dist: pytest-mock; extra == "ci"
Requires-Dist: faker; extra == "ci"
Dynamic: license-file
